stab/__init__.py
stab/main.py
stab/stab.py
stab/watchman.py
stab-1.2.1.dist-info/DESCRIPTION.rst
stab-1.2.1.dist-info/METADATA
stab-1.2.1.dist-info/RECORD
stab-1.2.1.dist-info/WHEEL
stab-1.2.1.dist-info/entry_points.txt
stab-1.2.1.dist-info/metadata.json
stab-1.2.1.dist-info/top_level.txt
