Metadata-Version: 2.0
Name: stab
Version: 1.2.1
Summary: Start blogging with this simple static site generator
Home-page: https://github.com/oxalorg/stab
Author: oxalorg
Author-email: rogue@oxal.org
License: UNKNOWN
Download-URL: https://github.com/oxalorg/stab/tarball/1.2.1
Keywords: python,static,site,website,generator
Platform: UNKNOWN
Requires-Dist: jinja2
Requires-Dist: mistune
Requires-Dist: pyyaml
